opyenxes/__init__.py
opyenxes/cli.py
opyenxes/classification/XEventAndClassifier.py
opyenxes/classification/XEventAttributeClassifier.py
opyenxes/classification/XEventClass.py
opyenxes/classification/XEventClasses.py
opyenxes/classification/XEventLifeTransClassifier.py
opyenxes/classification/XEventNameClassifier.py
opyenxes/classification/XEventResourceClassifier.py
opyenxes/classification/__init__.py
opyenxes/data_in/XMxmlGZIPParser.py
opyenxes/data_in/XMxmlParser.py
opyenxes/data_in/XParserRegistry.py
opyenxes/data_in/XUniversalParser.py
opyenxes/data_in/XesXmlGZIPParser.py
opyenxes/data_in/XesXmlParser.py
opyenxes/data_in/__init__.py
opyenxes/extension/XExtension.py
opyenxes/extension/XExtensionManager.py
opyenxes/extension/XExtensionParser.py
opyenxes/extension/__init__.py
opyenxes/extension/std/XAbstractNestedAttributeSupport.py
opyenxes/extension/std/XConceptExtension.py
opyenxes/extension/std/XCostExtension.py
opyenxes/extension/std/XExtendedEvent.py
opyenxes/extension/std/XIdentityExtension.py
opyenxes/extension/std/XLifecycleExtension.py
opyenxes/extension/std/XMicroExtension.py
opyenxes/extension/std/XOrganizationalExtension.py
opyenxes/extension/std/XSemanticExtension.py
opyenxes/extension/std/XTimeExtension.py
opyenxes/extension/std/__init__.py
opyenxes/factory/XFactory.py
opyenxes/factory/XFactoryRegistry.py
opyenxes/factory/__init__.py
opyenxes/id/XID.py
opyenxes/id/XIDFactory.py
opyenxes/id/__init__.py
opyenxes/info/XAttributeInfo.py
opyenxes/info/XAttributeNameMap.py
opyenxes/info/XGlobalAttributeNameMap.py
opyenxes/info/XLogInfo.py
opyenxes/info/XLogInfoFactory.py
opyenxes/info/XTimeBounds.py
opyenxes/info/__init__.py
opyenxes/log/XLogging.py
opyenxes/log/XStdoutLoggingListener.py
opyenxes/log/__init__.py
opyenxes/model/XAttributable.py
opyenxes/model/XAttribute.py
opyenxes/model/XAttributeBoolean.py
opyenxes/model/XAttributeCollection.py
opyenxes/model/XAttributeContainer.py
opyenxes-0.1.6.dist-info/DESCRIPTION.rst
opyenxes-0.1.6.dist-info/METADATA
opyenxes-0.1.6.dist-info/RECORD
opyenxes-0.1.6.dist-info/WHEEL
opyenxes-0.1.6.dist-info/entry_points.txt
opyenxes-0.1.6.dist-info/metadata.json
opyenxes-0.1.6.dist-info/top_level.txt
