Metadata-Version: 2.0
Name: opyenxes
Version: 0.1.6
Summary: A python implementation of the XES standard based on the Java implementation OpenXes.
Home-page: https://github.com/opyenxes/OpyenXes
Author: Process Mining UC
Author-email: processmininguc@gmail.com
License: GNU General Public License v3
Keywords: opyenxes,xes,process mining
Platform: UNKNOWN
Classifier: Development Status :: 2 - Pre-Alpha
Classifier: Intended Audience :: Developers
Classifier: License :: OSI Approved :: GNU General Public License v3 (GPLv3)
Classifier: Natural Language :: English
Classifier: Programming Language :: Python :: 3
Classifier: Programming Language :: Python :: 3.3
Classifier: Programming Language :: Python :: 3.4
Classifier: Programming Language :: Python :: 3.5
Requires-Dist: Click (>=6.0)
